{
    "wallpaper": "/home/daniel/nextcloud/Media/Wallpapers/wallpapers/Titans/cthulu.png",
    "alpha": "70",
    "special": {
        "background": "#09060a",
        "foreground": "#becdca",
        "cursor": "#becdca"
    },
    "colors": {
        "color0": "#09060a",
        "color1": "#315960",
        "color2": "#4A4D52",
        "color3": "#54666B",
        "color4": "#637B82",
        "color5": "#6F9496",
        "color6": "#77BDCE",
        "color7": "#becdca",
        "color8": "#858f8d",
        "color9": "#315960",
        "color10": "#4A4D52",
        "color11": "#54666B",
        "color12": "#637B82",
        "color13": "#6F9496",
        "color14": "#77BDCE",
        "color15": "#becdca"
    }
}